complextensor/__init__.py
complextensor/complex_tensor.py
tests/__init__.py
tests/test_complex_tensor.py
complextensor-0.1.0.dist-info/LICENSE
complextensor-0.1.0.dist-info/METADATA
complextensor-0.1.0.dist-info/WHEEL
complextensor-0.1.0.dist-info/entry_points.txt
complextensor-0.1.0.dist-info/top_level.txt
complextensor-0.1.0.dist-info/RECORD
