Metadata-Version: 2.1
Name: complextensor
Version: 0.1.0
Summary: A PyTorch-based library for complex tensor operations.
Author-email: bluecow009 <0xbluecow@protonmail.com>
Project-URL: Homepage, https://github.com/NeoVertex1/ComplexTensor
Project-URL: Documentation, https://complextensor.readthedocs.io
Project-URL: Repository, https://github.com/NeoVertex1/ComplexTensor
Project-URL: Bug Tracker, https://github.com/NeoVertex1/ComplexTensor/issues
Keywords: complex,tensor,pytorch,machine learning,signal processing
Classifier: Development Status :: 4 - Beta
Classifier: Intended Audience :: Developers
Classifier: Intended Audience :: Science/Research
Classifier: License :: OSI Approved :: MIT License
Classifier: Programming Language :: Python :: 3
Classifier: Programming Language :: Python :: 3.6
Classifier: Programming Language :: Python :: 3.7
Classifier: Programming Language :: Python :: 3.8
Classifier: Programming Language :: Python :: 3.9
Classifier: Programming Language :: Python :: 3.10
Classifier: Operating System :: OS Independent
Classifier: Topic :: Scientific/Engineering :: Mathematics
Classifier: Topic :: Scientific/Engineering :: Artificial Intelligence
Requires-Python: >=3.6
License-File: LICENSE
Requires-Dist: torch>=1.8.0
Requires-Dist: numpy>=1.18.0
